research/__init__.py
research/algorithm/__init__.py
research/algorithm/research_algorithm.py
research/dataset/__init__.py
research/dataset/research_dataset.py
research/experiment/__init__.py
research/experiment/research_experiment.py
tests/__init__.py
tests/test_estimator.py
awesome_research_demo_package-0.0.4.dist-info/METADATA
awesome_research_demo_package-0.0.4.dist-info/WHEEL
awesome_research_demo_package-0.0.4.dist-info/top_level.txt
awesome_research_demo_package-0.0.4.dist-info/RECORD
